{
  "Main": {
    "title1": {
      "type": "StructuredText",
      "config": {
        "single": "heading1, heading2, heading3, heading4, heading5, heading6",
        "label": "Title",
        "placeholder": "Main page title"
      }
    },
    "uid": {
      "type": "UID",
      "config": {
        "label": "URL",
        "placeholder": "UID"
      }
    },
    "body": {
      "type": "Slices",
      "fieldset": "Slice zone",
      "config": {
        "labels": {
          "page_header": [],
          "hero": [],
          "full_width_content": [],
          "call_to_action": [],
          "product_carousel": [],
          "content___image": [],
          "latest_blog_posts": [],
          "testimonials": [],
          "info_section": [],
          "contact": [],
          "blog_archive": [],
          "boxes": [],
          "faq": [],
          "gallery": [],
          "partners": [],
          "map": [],
          "events": []
        },
        "choices": {
          "page_header": {
            "type": "Slice",
            "fieldset": "Page Header",
            "description": "Page Header",
            "icon": "power_input",
            "display": "list",
            "non-repeat": {
              "title1": {
                "type": "StructuredText",
                "config": {
                  "single": "heading1, heading2, heading3, heading4, heading5, heading6",
                  "label": "Title"
                }
              },
              "show_breadcrumbs": {
                "type": "Boolean",
                "config": {
                  "default_value": false,
                  "label": "Show Breadcrumbs"
                }
              },
              "content": {
                "type": "StructuredText",
                "config": {
                  "multi": "paragraph, preformatted, heading1, heading2, heading3, heading4, heading5, heading6, strong, em, hyperlink, image, embed, list-item, o-list-item, rtl",
                  "label": "Content"
                }
              }
            },
            "repeat": {}
          },
          "hero": {
            "type": "Slice",
            "fieldset": "Hero",
            "description": "Main Hero with image",
            "icon": "face",
            "display": "list",
            "non-repeat": {
              "title2": {
                "type": "StructuredText",
                "config": {
                  "single": "heading1, heading2, heading3, heading4, heading5, heading6",
                  "label": "Title",
                  "placeholder": "Main page title"
                }
              },
              "content": {
                "type": "StructuredText",
                "config": {
                  "multi": "paragraph, preformatted, heading1, heading2, heading3, heading4, heading5, heading6, strong, em, hyperlink, image, embed, list-item, o-list-item, rtl",
                  "label": "Content"
                }
              },
              "image1": {
                "type": "Image",
                "config": {
                  "constraint": {},
                  "thumbnails": [],
                  "label": "Image"
                }
              }
            },
            "repeat": {}
          },
          "full_width_content": {
            "type": "Slice",
            "fieldset": "Full Width Content",
            "description": "Full Width Content",
            "icon": "subject",
            "display": "list",
            "non-repeat": {
              "content": {
                "type": "StructuredText",
                "config": {
                  "multi": "paragraph, preformatted, heading1, heading2, heading3, heading4, heading5, heading6, strong, em, hyperlink, image, embed, list-item, o-list-item, rtl",
                  "label": "Content"
                }
              }
            },
            "repeat": {}
          },
          "call_to_action": {
            "type": "Slice",
            "fieldset": "Call To Action",
            "description": "Call To Action Element",
            "icon": "priority_high",
            "display": "list",
            "non-repeat": {
              "content": {
                "type": "StructuredText",
                "config": {
                  "multi": "paragraph, preformatted, heading1, heading2, heading3, heading4, heading5, heading6, strong, em, hyperlink, image, embed, list-item, o-list-item, rtl",
                  "label": "Content"
                }
              }
            },
            "repeat": {
              "button_text": {
                "type": "Text",
                "config": {
                  "label": "Button Text"
                }
              },
              "link": {
                "type": "Link",
                "config": {
                  "select": "document",
                  "label": "Link"
                }
              },
              "alt_text": {
                "type": "Text",
                "config": {
                  "label": "Alt Text"
                }
              }
            }
          },
          "product_carousel": {
            "type": "Slice",
            "fieldset": "Product Carousel",
            "description": "Products carousel",
            "icon": "view_carousel",
            "display": "list",
            "non-repeat": {
              "overtitle": {
                "type": "StructuredText",
                "config": {
                  "single": "heading1, heading2, heading3, heading4, heading5, heading6",
                  "label": "Overtitle"
                }
              },
              "title1": {
                "type": "StructuredText",
                "config": {
                  "single": "heading1, heading2, heading3, heading4, heading5, heading6",
                  "label": "Title"
                }
              },
              "button_text": {
                "type": "Text",
                "config": {
                  "label": "Button Text"
                }
              },
              "link": {
                "type": "Link",
                "config": {
                  "label": "Link"
                }
              }
            },
            "repeat": {
              "product": {
                "type": "IntegrationFields",
                "config": {
                  "catalog": "freshonline--freshonline",
                  "label": "Product"
                }
              }
            }
          },
          "content___image": {
            "type": "Slice",
            "fieldset": "Content / Image",
            "description": "Image with side content",
            "icon": "art_track",
            "display": "list",
            "non-repeat": {
              "content": {
                "type": "StructuredText",
                "config": {
                  "multi": "paragraph, preformatted, heading1, heading2, heading3, heading4, heading5, heading6, strong, em, hyperlink, list-item, o-list-item, rtl",
                  "label": "Content"
                }
              },
              "image1": {
                "type": "Image",
                "config": {
                  "constraint": {},
                  "thumbnails": [],
                  "label": "Image"
                }
              },
              "reversed": {
                "type": "Boolean",
                "config": {
                  "placeholder_false": "Image on the left",
                  "placeholder_true": "Image on the right",
                  "default_value": false,
                  "label": "Reversed"
                }
              }
            },
            "repeat": {
              "link": {
                "type": "Link",
                "config": {
                  "label": "Link"
                }
              },
              "alt_link": {
                "type": "Text",
                "config": {
                  "label": "Alt Link"
                }
              },
              "button_text": {
                "type": "Text",
                "config": {
                  "label": "Button Text"
                }
              },
              "type": {
                "type": "Select",
                "config": {
                  "options": ["Full", "Outlined"],
                  "default_value": "Full",
                  "label": "type"
                }
              }
            }
          },
          "latest_blog_posts": {
            "type": "Slice",
            "fieldset": "Latest Blog Posts",
            "description": "Show latest blog posts",
            "icon": "trending_up",
            "display": "list",
            "non-repeat": {
              "subtitle": {
                "type": "StructuredText",
                "config": {
                  "single": "heading1, heading2, heading3, heading4, heading5, heading6",
                  "label": "Subtitle"
                }
              },
              "title1": {
                "type": "StructuredText",
                "config": {
                  "single": "heading1, heading2, heading3, heading4, heading5, heading6",
                  "label": "Title"
                }
              },
              "button_text": {
                "type": "Text",
                "config": {
                  "label": "Button Text"
                }
              }
            },
            "repeat": {}
          },
          "testimonials": {
            "type": "Slice",
            "fieldset": "Testimonials",
            "description": "Testimonials Carousel",
            "icon": "speaker_notes",
            "display": "list",
            "non-repeat": {
              "title1": {
                "type": "StructuredText",
                "config": {
                  "single": "heading1, heading2, heading3, heading4, heading5, heading6",
                  "label": "Title"
                }
              }
            },
            "repeat": {}
          },
          "info_section": {
            "type": "Slice",
            "fieldset": "Info Section",
            "description": "Information with links",
            "icon": "info_outline",
            "non-repeat": {
              "subtitle": {
                "type": "StructuredText",
                "config": {
                  "single": "heading6",
                  "label": "Subtitle"
                }
              },
              "title1": {
                "type": "StructuredText",
                "config": {
                  "single": "heading2",
                  "label": "Title"
                }
              },
              "button_text": {
                "type": "Text",
                "config": {
                  "label": "Button Text"
                }
              },
              "link": {
                "type": "Link",
                "config": {
                  "label": "Link"
                }
              },
              "alt_link": {
                "type": "Text",
                "config": {
                  "label": "Alt Link"
                }
              }
            },
            "repeat": {
              "icon": {
                "type": "Select",
                "config": {
                  "options": ["Account", "Delivery", "Fresh", "Shop"],
                  "default_value": "Account",
                  "label": "Icon"
                }
              },
              "content": {
                "type": "StructuredText",
                "config": {
                  "single": "heading5, heading6",
                  "label": "Content"
                }
              }
            }
          },
          "contact": {
            "type": "Slice",
            "fieldset": "Contact",
            "description": "Contact Section",
            "icon": "markunread_mailbox",
            "display": "list",
            "non-repeat": {
              "title2": {
                "type": "StructuredText",
                "config": {
                  "single": "heading1, heading2, heading3, heading4, heading5, heading6",
                  "label": "Title"
                }
              },
              "content": {
                "type": "StructuredText",
                "config": {
                  "multi": "paragraph, preformatted, heading1, heading2, heading3, heading4, heading5, heading6, strong, em, hyperlink, image, embed, list-item, o-list-item, rtl",
                  "allowTargetBlank": true,
                  "label": "Content"
                }
              }
            },
            "repeat": {
              "type": {
                "type": "Select",
                "config": {
                  "options": ["email", "phone", "address"],
                  "default_value": "email",
                  "label": "type",
                  "placeholder": "select type of contact item"
                }
              },
              "content": {
                "type": "StructuredText",
                "config": {
                  "multi": "paragraph, preformatted, heading1, heading2, heading3, heading4, heading5, heading6, strong, em, hyperlink, image, embed, list-item, o-list-item, rtl",
                  "allowTargetBlank": true,
                  "label": "Content"
                }
              },
              "title2": {
                "type": "StructuredText",
                "config": {
                  "single": "heading1, heading2, heading3, heading4, heading5, heading6",
                  "label": "Title"
                }
              }
            }
          },
          "blog_archive": {
            "type": "Slice",
            "fieldset": "Blog Archive",
            "description": "Render blog archive",
            "icon": "apps",
            "display": "list",
            "non-repeat": {},
            "repeat": {}
          },
          "boxes": {
            "type": "Slice",
            "fieldset": "Boxes",
            "description": "Limited Delivery Ideas Section",
            "icon": "line_style",
            "display": "list",
            "non-repeat": {
              "title1": {
                "type": "StructuredText",
                "config": {
                  "single": "heading1, heading2",
                  "label": "Title"
                }
              },
              "subtitle": {
                "type": "StructuredText",
                "config": {
                  "multi": "paragraph, strong",
                  "label": "Subtitle"
                }
              },
              "content": {
                "type": "StructuredText",
                "config": {
                  "multi": "paragraph, strong, hyperlink",
                  "label": "Content"
                }
              }
            },
            "repeat": {
              "box": {
                "type": "Text",
                "config": {
                  "label": "Box"
                }
              }
            }
          },
          "faq": {
            "type": "Slice",
            "fieldset": "FAQ",
            "description": "Frequently Asked Questions",
            "icon": "question_answer",
            "non-repeat": {},
            "repeat": {
              "question": {
                "type": "Text",
                "config": {
                  "label": "Question"
                }
              },
              "answer": {
                "type": "StructuredText",
                "config": {
                  "multi": "paragraph, strong, em, list-item, o-list-item",
                  "label": "Answer"
                }
              }
            }
          },
          "gallery": {
            "type": "Slice",
            "fieldset": "Gallery",
            "description": "Image gallery",
            "icon": "camera_alt",
            "display": "list",
            "non-repeat": {
              "lightbox": {
                "type": "Select",
                "config": {
                  "options": ["true", "false"],
                  "default_value": "true",
                  "label": "Lightbox",
                  "placeholder": "Choose if the gallery should support lightbox feature"
                }
              },
              "title2": {
                "type": "StructuredText",
                "config": {
                  "single": "heading1, heading2, heading3, heading4, heading5, heading6",
                  "label": "Title"
                }
              },
              "link": {
                "type": "Link",
                "config": {
                  "allowTargetBlank": true,
                  "label": "link",
                  "placeholder": "link"
                }
              },
              "alt_link": {
                "type": "Text",
                "config": {
                  "label": "Alt link"
                }
              },
              "content": {
                "type": "StructuredText",
                "config": {
                  "multi": "paragraph, preformatted, heading1, heading2, heading3, heading4, heading5, heading6, strong, em, hyperlink, image, embed, list-item, o-list-item, rtl",
                  "label": "Content"
                }
              }
            },
            "repeat": {
              "image1": {
                "type": "Image",
                "config": {
                  "constraint": {},
                  "thumbnails": [],
                  "label": "Image"
                }
              }
            }
          },
          "partners": {
            "type": "Slice",
            "fieldset": "GridItems",
            "description": "Image with heading and description element",
            "icon": "face",
            "display": "list",
            "non-repeat": {},
            "repeat": {
              "image1": {
                "type": "Image",
                "config": {
                  "constraint": {},
                  "thumbnails": [],
                  "label": "Image"
                }
              },
              "title2": {
                "type": "StructuredText",
                "config": {
                  "single": "heading1, heading2, heading3, heading4, heading5, heading6",
                  "label": "Title"
                }
              },
              "content": {
                "type": "StructuredText",
                "config": {
                  "multi": "paragraph, preformatted, heading1, heading2, heading3, heading4, heading5, heading6, strong, em, hyperlink, image, embed, list-item, o-list-item, rtl",
                  "allowTargetBlank": true,
                  "label": "Content"
                }
              },
              "type": {
                "type": "Select",
                "config": {
                  "options": ["partner", "team"],
                  "default_value": "partner",
                  "label": "type"
                }
              }
            }
          },
          "map": {
            "type": "Slice",
            "fieldset": "Map",
            "description": "Map section",
            "icon": "map",
            "display": "list",
            "non-repeat": {
              "title2": {
                "type": "StructuredText",
                "config": {
                  "single": "heading1, heading2, heading3, heading4, heading5, heading6",
                  "label": "Title"
                }
              },
              "content": {
                "type": "StructuredText",
                "config": {
                  "multi": "paragraph, preformatted, heading1, heading2, heading3, heading4, heading5, heading6, strong, em, hyperlink, image, embed, list-item, o-list-item, rtl",
                  "allowTargetBlank": true,
                  "label": "Content"
                }
              }
            },
            "repeat": {}
          },
          "events": {
            "type": "Slice",
            "fieldset": "Events",
            "description": "Events section",
            "icon": "event_available",
            "display": "list",
            "non-repeat": {
              "title_left": {
                "type": "StructuredText",
                "config": {
                  "single": "heading1, heading2, heading3, heading4, heading5, heading6",
                  "label": "Title left"
                }
              },
              "content": {
                "type": "StructuredText",
                "config": {
                  "multi": "paragraph, preformatted, heading1, heading2, heading3, heading4, heading5, heading6, strong, em, hyperlink, image, embed, list-item, o-list-item, rtl",
                  "label": "Content"
                }
              },
              "title_right": {
                "type": "StructuredText",
                "config": {
                  "single": "heading1, heading2, heading3, heading4, heading5, heading6",
                  "label": "Title Right"
                }
              }
            },
            "repeat": {
              "content": {
                "type": "StructuredText",
                "config": {
                  "multi": "paragraph, preformatted, heading1, heading2, heading3, heading4, heading5, heading6, strong, em, hyperlink, image, embed, list-item, o-list-item, rtl",
                  "label": "Content"
                }
              },
              "title2": {
                "type": "StructuredText",
                "config": {
                  "single": "heading1, heading2, heading3, heading4, heading5, heading6",
                  "label": "Title"
                }
              }
            }
          }
        }
      }
    }
  },
  "SEO": {
    "title": {
      "type": "StructuredText",
      "config": {
        "single": "heading1, heading2, heading3, heading4, heading5, heading6",
        "label": "Title"
      }
    },
    "description": {
      "type": "Text",
      "config": {
        "label": "Description"
      }
    },
    "image": {
      "type": "Image",
      "config": {
        "constraint": {},
        "thumbnails": [],
        "label": "Image"
      }
    }
  }
}
